clickable/__init__.py
clickable/click/__init__.py
clickable/coloredlogs/__init__.py
clickable/sphinx/__init__.py
clickable/syncing/__init__.py
clickable/utils/__init__.py
clickable/virtualenv/__init__.py
clickable/virtualenv/commands.py
clickable/virtualenv/virtualenv.py
clickable-1.8.dist-info/LICENSE
clickable-1.8.dist-info/METADATA
clickable-1.8.dist-info/WHEEL
clickable-1.8.dist-info/entry_points.txt
clickable-1.8.dist-info/top_level.txt
clickable-1.8.dist-info/RECORD
