Metadata-Version: 2.1
Name: clickable
Version: 1.8
Summary: Helper scripts to write click applications development's environment
Home-page: https://github.com/lalmeras/clickable
Author: Laurent Almeras
Author-email: lalmeras@gmail.com
License: BSD license
Keywords: clickable
Classifier: Development Status :: 2 - Pre-Alpha
Classifier: Intended Audience :: Developers
Classifier: License :: OSI Approved :: BSD License
Classifier: Natural Language :: English
Classifier: Programming Language :: Python :: 3
Classifier: Programming Language :: Python :: 3.6
Classifier: Programming Language :: Python :: 3.7
Requires-Python: >=3.6
License-File: LICENSE
Requires-Dist: click ==8.0.1
Requires-Dist: blessings ==1.7
Requires-Dist: coloredlogs ==15.0.1
Requires-Dist: PyYAML ==6.0.1
